LICENSE
MANIFEST.in
README.md
requirements.txt
setup.py
leetDecoding/__init__.py
leetDecoding/efficient_linear_decoding.py
leetDecoding.egg-info/PKG-INFO
leetDecoding.egg-info/SOURCES.txt
leetDecoding.egg-info/dependency_links.txt
leetDecoding.egg-info/requires.txt
leetDecoding.egg-info/top_level.txt
leetDecoding/methods/BlockBased.py
leetDecoding/methods/FleetAttention.py
leetDecoding/methods/FleetAttention_triton.py
leetDecoding/methods/Recursion.py
leetDecoding/methods/__init__.py
leetDecoding/methods/causal_dot_product.py
leetDecoding/methods/causal_dot_product_torch.py
leetDecoding/methods/causal_product_cuda.cu
leetDecoding/methods/causal_product_cuda_with_decay_fp16.cu
leetDecoding/methods/causal_product_cuda_with_decay_fp32.cu
leetDecoding/methods/lightningAttention2.py
leetDecoding/methods/lightningAttention2_torch.py
leetDecoding/methods/linear_attn.py
leetDecoding/test/test_method.py