Metadata-Version: 2.1
Name: leetDecoding
Version: 0.0.3
Summary: Efficient computation library for linear attention.
Home-page: https://github.com/Computational-Machine-Intelligence/LeetDecoding
Author: Jiaping Wang
Author-email: wjp666.s@gmail.com
License: MIT Licence
Keywords: pip,leetDecoding,LeetDecoding,efficient_linear_decoding
Platform: any
Requires-Python: >=3.8
License-File: LICENSE
